voice_of_python/__init__.py
voice_of_python/voice_of_python.py
voice_of_python-0.1.0.dist-info/licenses/LICENSE
voice_of_python-0.1.0.dist-info/METADATA
voice_of_python-0.1.0.dist-info/WHEEL
voice_of_python-0.1.0.dist-info/top_level.txt
voice_of_python-0.1.0.dist-info/RECORD
