Metadata-Version: 2.4
Name: voice_of_python
Version: 0.1.0
Summary: Offline multilingual voice bot with Vosk ASR and pyttsx3 TTS
Home-page: https://github.com/henry-n2/voice_of_python
Author: Ujjal Bhattacharya
Author-email: ujjalbhattacharya525@gmail.com
Classifier: Programming Language :: Python :: 3
Classifier: Operating System :: OS Independent
Classifier: Topic :: Software Development :: Libraries
Requires-Python: >=3.7
License-File: LICENSE
Requires-Dist: vosk
Requires-Dist: langid
Requires-Dist: pyttsx3
Requires-Dist: sounddevice
Requires-Dist: numpy
Requires-Dist: soundfile
Dynamic: author
Dynamic: author-email
Dynamic: classifier
Dynamic: description
Dynamic: description-content-type
Dynamic: home-page
Dynamic: license-file
Dynamic: requires-dist
Dynamic: requires-python
Dynamic: summary
